bonsai/__init__.py
bonsai/__main__.py
bonsai/analysis.py
bonsai/bonsai.py
bonsai/model.py
bonsai/parser.py
bonsai/cpp/__init__.py
bonsai/cpp/analysis.py
bonsai/cpp/clang_parser.py
bonsai/cpp/model.py
bonsai/py/__init__.py
bonsai/py/builder.py
bonsai/py/model.py
bonsai/py/py_parser.py
bonsai/py/visitor.py
bonsai_code-0.6.8.dist-info/LICENSE
bonsai_code-0.6.8.dist-info/METADATA
bonsai_code-0.6.8.dist-info/WHEEL
bonsai_code-0.6.8.dist-info/entry_points.txt
bonsai_code-0.6.8.dist-info/top_level.txt
bonsai_code-0.6.8.dist-info/zip-safe
bonsai_code-0.6.8.dist-info/RECORD
