Metadata-Version: 2.1
Name: bonsai-code
Version: 0.6.8
Summary: Static analysis library.
Home-page: https://github.com/git-afsantos/bonsai
Author: Andre Santos
Author-email: haros.framework@gmail.com
License: MIT
Keywords: static-analysis ast parsing
Platform: UNKNOWN
License-File: LICENSE
